aviv_cdk/__init__.py
aviv_cdk/core.py
aviv_cdk/ecs_construct.py
aviv_cdk/rds_construct.py
aviv_cdk/route53.py
aviv_cdk/secretsmanager.py
aviv_cdk/cicd/__init__.py
aviv_cdk/cicd/codebuild.py
aviv_cdk/cicd/connections.py
aviv_cdk/cicd/notif.py
aviv_cdk/cicd/sources.py
aviv_cdk/cicd/stack.py
aviv_cdk/iam/__init__.py
aviv_cdk/iam/athena_glue.py
aviv_cdk/iam/credentials.py
aviv_cdk/iam/idp.py
aviv_cdk/iam/role.py
aviv_cdk/lambdas/__init__.py
aviv_cdk/lambdas/base.py
aviv_cdk/stepfunctions/__init__.py
aviv_cdk/stepfunctions/base.py
aviv_cdk/stepfunctions/statemachine.py
aviv_cdk-0.3.13.dist-info/LICENSE
aviv_cdk-0.3.13.dist-info/METADATA
aviv_cdk-0.3.13.dist-info/WHEEL
aviv_cdk-0.3.13.dist-info/top_level.txt
aviv_cdk-0.3.13.dist-info/RECORD
