Metadata-Version: 2.1
Name: aviv-cdk
Version: 0.3.13
Summary: Aviv CDK Python library
Home-page: https://github.com/aviv-group/aviv-cdk-python
Author: Jules Clement
Author-email: jules.clement@aviv-group.com
Classifier: Development Status :: 4 - Beta
Classifier: Intended Audience :: Developers
Classifier: Intended Audience :: Information Technology
Classifier: Intended Audience :: System Administrators
Classifier: License :: OSI Approved :: MIT License
Classifier: Programming Language :: Python :: 3 :: Only
Classifier: Programming Language :: Python :: 3.8
Classifier: Operating System :: OS Independent
Classifier: Topic :: Utilities
Classifier: Topic :: System
Classifier: Topic :: System :: Systems Administration
Requires-Python: >=3.8
License-File: LICENSE
Requires-Dist: aws-cdk-lib (>=2.30.0)
Requires-Dist: boto3 (>=1.24.9)
Requires-Dist: botocore (>=1.27.9)
Requires-Dist: constructs (>=10.0.0)
Provides-Extra: data
Requires-Dist: awswrangler (>=2.16.0) ; extra == 'data'
